codefabric/__init__.py
codefabric/cli.py
codefabric/data/__init__.py
codefabric/data/commands.py
codefabric/graph/__init__.py
codefabric/graph/debug_and_fix_agent.py
codefabric/graph/developer_agent.py
codefabric/graph/sql_checkpointer.py
codefabric/logging/logger.py
codefabric/prompts/__init__.py
codefabric/prompts/create_project_plan_prompts.py
codefabric/prompts/decide_packages_prompts.py
codefabric/prompts/generate_file_code_prompts.py
codefabric/prompts/generate_gitignore_prompts.py
codefabric/types/__init__.py
codefabric/types/enums.py
codefabric/types/models.py
codefabric/types/output_formatters.py
codefabric/utils/command_runner.py
codefabric/utils/io_helper.py
codefabric-0.2.2.dist-info/licenses/LICENSE
codefabric-0.2.2.dist-info/METADATA
codefabric-0.2.2.dist-info/WHEEL
codefabric-0.2.2.dist-info/entry_points.txt
codefabric-0.2.2.dist-info/top_level.txt
codefabric-0.2.2.dist-info/RECORD
