Metadata-Version: 2.4
Name: codefabric
Version: 0.2.2
Summary: CodeFabric is an AI-powered code generation framework that spins up full projects from natural language requirements using LangGraph workflows.
Author-email: Saurav Kumar Srivastava <sksrivastava.me@gmail.com>
License-Expression: MIT
Project-URL: Homepage, https://github.com/S-k-Srivastava/CodeFabric
Project-URL: Repository, https://github.com/S-k-Srivastava/CodeFabric
Project-URL: Issues, https://github.com/S-k-Srivastava/CodeFabric/issues
Keywords: ai,codegen,langgraph,developer tools,automation
Requires-Python: >=3.12
License-File: LICENSE
Requires-Dist: build>=1.2.2.post1
Requires-Dist: colorlog>=6.9.0
Requires-Dist: ipykernel>=6.29.5
Requires-Dist: langchain>=0.3.25
Requires-Dist: langchain-community>=0.3.23
Requires-Dist: langchain-openai>=0.3.16
Requires-Dist: langgraph>=0.4.2
Requires-Dist: langgraph-checkpoint-sqlite>=2.0.7
Requires-Dist: msgpack>=1.1.0
Requires-Dist: python-dotenv>=1.1.0
Requires-Dist: rich>=14.0.0
Requires-Dist: textual>=3.5.0
Requires-Dist: twine>=6.1.0
Requires-Dist: uuid>=1.30
Dynamic: license-file
